lilliepy_state/__init__.py
lilliepy_state/main.py
lilliepy_state-0.1.dist-info/METADATA
lilliepy_state-0.1.dist-info/WHEEL
lilliepy_state-0.1.dist-info/top_level.txt
lilliepy_state-0.1.dist-info/RECORD
