Metadata-Version: 2.1
Name: lilliepy-state
Version: 0.1
Summary: state manager for lilliepy framework
Home-page: https://github.com/websitedeb/lilliepy-state
Author: Sarthak Ghoshal
Author-email: sarthak22.ghoshal@gmail.com
License: MIT
Keywords: lilliepy,lilliepy-state,reactpy
Classifier: Programming Language :: Python :: 3
Classifier: License :: OSI Approved :: MIT License
Classifier: Operating System :: OS Independent
Requires-Python: >=3.6
Requires-Dist: reactpy
